prvdoracle/__init__.py
prvdoracle/main.py
prvdoracle-0.0.1.dist-info/LICENSE
prvdoracle-0.0.1.dist-info/METADATA
prvdoracle-0.0.1.dist-info/WHEEL
prvdoracle-0.0.1.dist-info/entry_points.txt
prvdoracle-0.0.1.dist-info/top_level.txt
prvdoracle-0.0.1.dist-info/RECORD
