Metadata-Version: 2.1
Name: prvdoracle
Version: 0.0.1
Summary: Provide oracle base architecture and runloop
Home-page: https://github.com/provideservices/provide-oracle
Author: Kyle Thomas
Author-email: kyle@provide.services
License: UNKNOWN
Platform: UNKNOWN
Requires-Dist: backports-abc
Requires-Dist: prvd
Requires-Dist: tornado
